medeval/__init__.py
medeval/py.typed
medeval/cli/__init__.py
medeval/cli/evaluate.py
medeval/cli/main.py
medeval/core/__init__.py
medeval/core/aggregate.py
medeval/core/containers.py
medeval/core/interop.py
medeval/core/io.py
medeval/core/typing.py
medeval/core/utils.py
medeval/metrics/__init__.py
medeval/metrics/classification.py
medeval/metrics/detection.py
medeval/metrics/registration.py
medeval/metrics/segmentation.py
medeval/vis/__init__.py
medeval/vis/calibration.py
medeval/vis/curves.py
medeval/vis/histograms.py
medeval/vis/overlays.py
medeval-0.1.7.dist-info/licenses/LICENSE
medeval-0.1.7.dist-info/METADATA
medeval-0.1.7.dist-info/WHEEL
medeval-0.1.7.dist-info/entry_points.txt
medeval-0.1.7.dist-info/top_level.txt
medeval-0.1.7.dist-info/RECORD
