Metadata-Version: 2.4
Name: medeval
Version: 0.1.7
Summary: PyTorch-native library for medical imaging evaluation metrics
Author: MedEval Contributors
License-Expression: Apache-2.0
Classifier: Development Status :: 3 - Alpha
Classifier: Intended Audience :: Science/Research
Classifier: Programming Language :: Python :: 3
Classifier: Programming Language :: Python :: 3.9
Classifier: Programming Language :: Python :: 3.10
Classifier: Programming Language :: Python :: 3.11
Classifier: Programming Language :: Python :: 3.12
Classifier: Topic :: Scientific/Engineering :: Medical Science Apps.
Requires-Python: >=3.9
License-File: LICENSE
Requires-Dist: numpy>=1.21.0
Requires-Dist: scipy>=1.9.0
Requires-Dist: scikit-learn>=1.0.0
Provides-Extra: core
Requires-Dist: numpy>=1.21.0; extra == "core"
Requires-Dist: scipy>=1.9.0; extra == "core"
Requires-Dist: scikit-learn>=1.0.0; extra == "core"
Provides-Extra: torch
Requires-Dist: torch>=2.0.0; extra == "torch"
Provides-Extra: io
Requires-Dist: nibabel>=5.0.0; extra == "io"
Requires-Dist: SimpleITK>=2.3.0; extra == "io"
Provides-Extra: seg
Requires-Dist: nibabel>=5.0.0; extra == "seg"
Requires-Dist: SimpleITK>=2.3.0; extra == "seg"
Provides-Extra: cli
Requires-Dist: tqdm>=4.65.0; extra == "cli"
Requires-Dist: pyyaml>=6.0; extra == "cli"
Requires-Dist: pandas>=1.5.0; extra == "cli"
Provides-Extra: vis
Requires-Dist: matplotlib>=3.8.0; extra == "vis"
Provides-Extra: dicom
Requires-Dist: pydicom>=2.3.0; extra == "dicom"
Provides-Extra: all
Requires-Dist: torch>=2.0.0; extra == "all"
Requires-Dist: nibabel>=5.0.0; extra == "all"
Requires-Dist: SimpleITK>=2.3.0; extra == "all"
Requires-Dist: tqdm>=4.65.0; extra == "all"
Requires-Dist: pyyaml>=6.0; extra == "all"
Requires-Dist: pandas>=1.5.0; extra == "all"
Requires-Dist: matplotlib>=3.8.0; extra == "all"
Requires-Dist: pydicom>=2.3.0; extra == "all"
Provides-Extra: dev
Requires-Dist: torch>=2.0.0; extra == "dev"
Requires-Dist: nibabel>=5.0.0; extra == "dev"
Requires-Dist: SimpleITK>=2.3.0; extra == "dev"
Requires-Dist: tqdm>=4.65.0; extra == "dev"
Requires-Dist: pyyaml>=6.0; extra == "dev"
Requires-Dist: pandas>=1.5.0; extra == "dev"
Requires-Dist: matplotlib>=3.8.0; extra == "dev"
Requires-Dist: pydicom>=2.3.0; extra == "dev"
Requires-Dist: pytest>=7.4.0; extra == "dev"
Requires-Dist: pytest-cov>=4.1.0; extra == "dev"
Requires-Dist: pytest-xdist>=3.3.0; extra == "dev"
Requires-Dist: black>=23.0.0; extra == "dev"
Requires-Dist: ruff>=0.1.0; extra == "dev"
Requires-Dist: mypy>=1.5.0; extra == "dev"
Requires-Dist: pre-commit>=3.4.0; extra == "dev"
Requires-Dist: mkdocs>=1.5.0; extra == "dev"
Requires-Dist: mkdocs-material>=9.0.0; extra == "dev"
Requires-Dist: build>=1.0.0; extra == "dev"
Requires-Dist: twine>=6.0.0; extra == "dev"
Dynamic: license-file
